{
  "id": "62d35cf0-78dc-413b-9202-38cea35ad3d9",
  "uid": "id-quam-dicta",
  "type": "my-publication-type",
  "data": {
    "title": [
      {
        "type": "heading1",
        "text": "Target collaborative ROI",
        "spans": []
      }
    ],
    "content": [
      {
        "type": "heading1",
        "text": "Brand interactive partnerships",
        "spans": []
      },
      {
        "type": "paragraph",
        "text": "Sint nostrud et consequat aute in et irure est non consectetur.",
        "spans": []
      }
    ]
  }
}